[
  {
    "hospital": "BUTLER HOSPITAL",
    "ccn": "414000",
    "city": "PROVIDENCE",
    "county": "Providence",
    "zip": "02906",
    "state": "RI",
    "phone": "(401) 455-6270",
    "ownership": "Voluntary non-profit - Private",
    "hospital_type": "Psychiatric",
    "status": "statutory",
    "policy": null
  },
  {
    "hospital": "EMMA PENDLETON BRADLEY HOSPITAL",
    "ccn": "414003",
    "city": "EAST PROVIDENCE",
    "county": "Providence",
    "zip": "02915",
    "state": "RI",
    "phone": "(401) 432-1000",
    "ownership": "Voluntary non-profit - Private",
    "hospital_type": "Psychiatric",
    "status": "statutory",
    "policy": null
  },
  {
    "hospital": "KENT COUNTY MEMORIAL HOSPITAL",
    "ccn": "410009",
    "city": "WARWICK",
    "county": "Kent",
    "zip": "02886",
    "state": "RI",
    "phone": "(401) 737-7010",
    "ownership": "Proprietary",
    "hospital_type": "Acute Care Hospitals",
    "status": "statutory",
    "policy": null
  },
  {
    "hospital": "LANDMARK MEDICAL CENTER",
    "ccn": "410011",
    "city": "WOONSOCKET",
    "county": "Providence",
    "zip": "02895",
    "state": "RI",
    "phone": "(401) 769-4100",
    "ownership": "Voluntary non-profit - Private",
    "hospital_type": "Acute Care Hospitals",
    "status": "statutory",
    "policy": null
  },
  {
    "hospital": "NEWPORT HOSPITAL",
    "ccn": "410006",
    "city": "NEWPORT",
    "county": "Newport",
    "zip": "02840",
    "state": "RI",
    "phone": "(401) 846-6400",
    "ownership": "Voluntary non-profit - Private",
    "hospital_type": "Acute Care Hospitals",
    "status": "statutory",
    "policy": null
  },
  {
    "hospital": "OUR LADY OF FATIMA HOSPITAL",
    "ccn": "410005",
    "city": "NORTH PROVIDENCE",
    "county": "Providence",
    "zip": "02904",
    "state": "RI",
    "phone": "(401) 456-3000",
    "ownership": "Proprietary",
    "hospital_type": "Acute Care Hospitals",
    "status": "statutory",
    "policy": null
  },
  {
    "hospital": "RHODE ISLAND HOSPITAL",
    "ccn": "410007",
    "city": "PROVIDENCE",
    "county": "Providence",
    "zip": "02902",
    "state": "RI",
    "phone": "(401) 444-4000",
    "ownership": "Voluntary non-profit - Private",
    "hospital_type": "Acute Care Hospitals",
    "status": "statutory",
    "policy": null
  },
  {
    "hospital": "ROGER WILLIAMS MEDICAL CENTER",
    "ccn": "410004",
    "city": "PROVIDENCE",
    "county": "Providence",
    "zip": "02908",
    "state": "RI",
    "phone": "(401) 456-2025",
    "ownership": "Proprietary",
    "hospital_type": "Acute Care Hospitals",
    "status": "statutory",
    "policy": null
  },
  {
    "hospital": "SOUTH COUNTY HOSPITAL INC",
    "ccn": "410008",
    "city": "WAKEFIELD",
    "county": "Washington",
    "zip": "02879",
    "state": "RI",
    "phone": "(401) 782-8000",
    "ownership": "Voluntary non-profit - Private",
    "hospital_type": "Acute Care Hospitals",
    "status": "statutory",
    "policy": null
  },
  {
    "hospital": "THE MIRIAM HOSPITAL",
    "ccn": "410012",
    "city": "PROVIDENCE",
    "county": "Providence",
    "zip": "02906",
    "state": "RI",
    "phone": "(401) 793-2500",
    "ownership": "Voluntary non-profit - Private",
    "hospital_type": "Acute Care Hospitals",
    "status": "statutory",
    "policy": null
  },
  {
    "hospital": "WESTERLY HOSPITAL",
    "ccn": "410013",
    "city": "WESTERLY",
    "county": "Washington",
    "zip": "02891",
    "state": "RI",
    "phone": "(401) 596-6000",
    "ownership": "Voluntary non-profit - Private",
    "hospital_type": "Acute Care Hospitals",
    "status": "statutory",
    "policy": null
  },
  {
    "hospital": "WOMEN & INFANTS HOSPITAL OF RHODE ISLAND",
    "ccn": "410010",
    "city": "PROVIDENCE",
    "county": "Providence",
    "zip": "02905",
    "state": "RI",
    "phone": "(401) 274-1100",
    "ownership": "Voluntary non-profit - Private",
    "hospital_type": "Acute Care Hospitals",
    "status": "statutory",
    "policy": null
  }
]
